validbr/__init__.py
validbr-2.0.0.dist-info/METADATA
validbr-2.0.0.dist-info/WHEEL
validbr-2.0.0.dist-info/top_level.txt
validbr-2.0.0.dist-info/RECORD
