Metadata-Version: 2.1
Name: validbr
Version: 2.0.0
Summary: A comprehensive Brazilian validation library for Python
Home-page: https://github.com/validbr/validbr
Author: ValidBR Team
Author-email: julio@grupojpc.com.br
License: UNKNOWN
Project-URL: Bug Reports, https://github.com/validbr/validbr/issues
Project-URL: Source, https://github.com/validbr/validbr
Project-URL: Documentation, https://docs.validbr.com
Keywords: brazil,validation,cpf,cnpj,cep,phone,email,rg,ie,ddd,mask,sanitize
Platform: UNKNOWN
Classifier: Development Status :: 5 - Production/Stable
Classifier: Intended Audience :: Developers
Classifier: License :: OSI Approved :: MIT License
Classifier: Operating System :: OS Independent
Classifier: Programming Language :: Python :: 3
Classifier: Programming Language :: Python :: 3.7
Classifier: Programming Language :: Python :: 3.8
Classifier: Programming Language :: Python :: 3.9
Classifier: Programming Language :: Python :: 3.10
Classifier: Programming Language :: Python :: 3.11
Classifier: Topic :: Software Development :: Libraries :: Python Modules
Classifier: Topic :: Text Processing :: Filters
Requires-Python: >=3.7
Requires-Dist: requests (>=2.25.0)
Provides-Extra: dev
Requires-Dist: pytest (>=6.0.0) ; extra == 'dev'
Requires-Dist: pytest-cov (>=2.10.0) ; extra == 'dev'
Requires-Dist: black (>=21.0.0) ; extra == 'dev'
Requires-Dist: flake8 (>=3.8.0) ; extra == 'dev'
Requires-Dist: mypy (>=0.800) ; extra == 'dev'
